<?xml version="1.0" encoding="UTF-8"?>
<!DOCTYPE mapper PUBLIC "-//mybatis.org//DTD Mapper 3.0//EN" "http://mybatis.org/dtd/mybatis-3-mapper.dtd">
<mapper namespace="com.easy.work.province.dao.ProvinceDao">
  <resultMap id="BaseResultMap" type="com.easy.work.province.domain.ProvinceDomain">
    <!--
      WARNING - @mbg.generated
      This element is automatically generated by MyBatis Generator, do not modify.
      This element was generated on Fri Jun 15 09:13:25 CST 2018.
    -->
    <id column="id" jdbcType="BIGINT" property="id" />
    <result column="version" jdbcType="BIGINT" property="version" />
    <result column="code" jdbcType="VARCHAR" property="code" />
    <result column="create_time" jdbcType="TIMESTAMP" property="createTime" />
    <result column="name" jdbcType="VARCHAR" property="name" />
    <result column="op_id" jdbcType="VARCHAR" property="opId" />
    <result column="update_time" jdbcType="TIMESTAMP" property="updateTime" />
  </resultMap>
  <sql id="Base_Column_List">
    <!--
      WARNING - @mbg.generated
      This element is automatically generated by MyBatis Generator, do not modify.
      This element was generated on Fri Jun 15 09:13:25 CST 2018.
    -->
    id, version, code, create_time, name, op_id, update_time
  </sql>
  <select id="findCondition" parameterType="java.lang.Long" resultMap="BaseResultMap">
    <!--
      WARNING - @mbg.generated
      This element is automatically generated by MyBatis Generator, do not modify.
      This element was generated on Fri Jun 15 09:13:25 CST 2018.
    -->
    select 
    <include refid="Base_Column_List" />
    from province
    where id = #{id,jdbcType=BIGINT}
  </select>
  <select id="findList" parameterType="com.easy.work.province.domain.ProvinceDomain" resultMap="BaseResultMap">
    select
    <include refid="Base_Column_List" />
    from province
  </select>
  <delete id="delete" parameterType="java.lang.Long">
    <!--
      WARNING - @mbg.generated
      This element is automatically generated by MyBatis Generator, do not modify.
      This element was generated on Fri Jun 15 09:13:25 CST 2018.
    -->
    delete from province
    where id = #{id,jdbcType=BIGINT}
  </delete>
  <insert id="insert" parameterType="com.easy.work.province.domain.ProvinceDomain">
    <!--
      WARNING - @mbg.generated
      This element is automatically generated by MyBatis Generator, do not modify.
      This element was generated on Fri Jun 15 09:13:25 CST 2018.
    -->
    insert into province (id, version, code, 
      create_time, name, op_id, 
      update_time)
    values (#{id,jdbcType=BIGINT}, #{version,jdbcType=BIGINT}, #{code,jdbcType=VARCHAR}, 
      #{createTime,jdbcType=TIMESTAMP}, #{name,jdbcType=VARCHAR}, #{opId,jdbcType=VARCHAR}, 
      #{updateTime,jdbcType=TIMESTAMP})
  </insert>
  <insert id="insertSelective" parameterType="com.easy.work.province.domain.ProvinceDomain">
    <!--
      WARNING - @mbg.generated
      This element is automatically generated by MyBatis Generator, do not modify.
      This element was generated on Fri Jun 15 09:13:25 CST 2018.
    -->
    insert into province
    <trim prefix="(" suffix=")" suffixOverrides=",">
      <if test="id != null">
        id,
      </if>
      <if test="version != null">
        version,
      </if>
      <if test="code != null">
        code,
      </if>
      <if test="createTime != null">
        create_time,
      </if>
      <if test="name != null">
        name,
      </if>
      <if test="opId != null">
        op_id,
      </if>
      <if test="updateTime != null">
        update_time,
      </if>
    </trim>
    <trim prefix="values (" suffix=")" suffixOverrides=",">
      <if test="id != null">
        #{id,jdbcType=BIGINT},
      </if>
      <if test="version != null">
        #{version,jdbcType=BIGINT},
      </if>
      <if test="code != null">
        #{code,jdbcType=VARCHAR},
      </if>
      <if test="createTime != null">
        #{createTime,jdbcType=TIMESTAMP},
      </if>
      <if test="name != null">
        #{name,jdbcType=VARCHAR},
      </if>
      <if test="opId != null">
        #{opId,jdbcType=VARCHAR},
      </if>
      <if test="updateTime != null">
        #{updateTime,jdbcType=TIMESTAMP},
      </if>
    </trim>
  </insert>
  <update id="update" parameterType="com.easy.work.province.domain.ProvinceDomain">
    <!--
      WARNING - @mbg.generated
      This element is automatically generated by MyBatis Generator, do not modify.
      This element was generated on Fri Jun 15 09:13:25 CST 2018.
    -->
    update province
    <set>
      <if test="version != null">
        version = #{version,jdbcType=BIGINT},
      </if>
      <if test="code != null">
        code = #{code,jdbcType=VARCHAR},
      </if>
      <if test="createTime != null">
        create_time = #{createTime,jdbcType=TIMESTAMP},
      </if>
      <if test="name != null">
        name = #{name,jdbcType=VARCHAR},
      </if>
      <if test="opId != null">
        op_id = #{opId,jdbcType=VARCHAR},
      </if>
      <if test="updateTime != null">
        update_time = #{updateTime,jdbcType=TIMESTAMP},
      </if>
    </set>
    where id = #{id,jdbcType=BIGINT}
  </update>
</mapper>